npmvaliddep/__init__.py
npmvaliddep/argumentmapper.py
npmvaliddep/github.json
npmvaliddep/main.py
npmvaliddep/utils/__init__.py
npmvaliddep/utils/dependency_change.py
npmvaliddep/utils/github_url.py
npmvaliddep-2.1.3.dist-info/LICENSE.txt
npmvaliddep-2.1.3.dist-info/METADATA
npmvaliddep-2.1.3.dist-info/WHEEL
npmvaliddep-2.1.3.dist-info/entry_points.txt
npmvaliddep-2.1.3.dist-info/top_level.txt
npmvaliddep-2.1.3.dist-info/RECORD
