Metadata-Version: 2.1
Name: npmvaliddep
Version: 2.1.3
Summary: CLI Tools to check dependencies of a node project github repository
Home-page: https://github.com/dyte-submissions/dyte-vit-2022-Akshat1903
Author: Akshat Gupta
Author-email: akshatgupta1903@gmail.com
License: Apache License 2.0
Keywords: cli,github,npm,node,dependency
Classifier: Development Status :: 3 - Alpha
Classifier: Intended Audience :: Developers
Classifier: Topic :: Software Development :: Build Tools
Classifier: Topic :: System :: Shells
Classifier: Topic :: Utilities
Classifier: License :: OSI Approved :: Apache Software License
Classifier: Programming Language :: Python :: 3.7
Classifier: Programming Language :: Python :: 3.8
Classifier: Programming Language :: Python :: 3.9
Classifier: Programming Language :: Python :: 3.10
Requires-Python: >=3.7
License-File: LICENSE.txt
Requires-Dist: requests
Provides-Extra: dev
Requires-Dist: setuptools ; extra == 'dev'
Requires-Dist: twine ; extra == 'dev'
Requires-Dist: wheel ; extra == 'dev'
